StructuralGT/GT_Params.py
StructuralGT/GT_Params_multi.py
StructuralGT/GT_Params_noGUI.py
StructuralGT/GetWeights.py
StructuralGT/GetWeights_3d.py
StructuralGT/__init__.py
StructuralGT/__main__.py
StructuralGT/algorithm_benchmarks.py
StructuralGT/base.py
StructuralGT/convert.cp39-win_amd64.pyd
StructuralGT/error.py
StructuralGT/gui_3d_image.py
StructuralGT/gui_multi_image.py
StructuralGT/gui_single_image.py
StructuralGT/multi_image_settings.py
StructuralGT/network.py
StructuralGT/process_image.py
StructuralGT/sbox.py
StructuralGT/settings.py
StructuralGT/settings_3d.py
StructuralGT/single_image_looper.py
StructuralGT/skel_ID.py
StructuralGT/skel_ID_3d.py
StructuralGT/skel_features.py
StructuralGT/pytest/data/ANF/Image1 - SliceImage - 001.tif
StructuralGT/pytest/data/ANF/Image1 - SliceImage - 002.tif
StructuralGT/pytest/data/ANF/Image1 - SliceImage - 003.tif
StructuralGT/pytest/data/ANF/Image1 - SliceImage - 004.tif
StructuralGT/pytest/data/ANF/Image1 - SliceImage - 005.tif
StructuralGT/pytest/data/ANF/Image1 - SliceImage - 006.tif
StructuralGT/pytest/data/ANF/Image1 - SliceImage - 007.tif
StructuralGT/pytest/data/ANF/Image1 - SliceImage - 008.tif
StructuralGT/pytest/data/ANF/Image1 - SliceImage - 009.tif
StructuralGT/pytest/data/ANF/img_options.json
StructuralGT/pytest/data/AgNWN/10um.tif
StructuralGT/pytest/data/AgNWN/img_options.json
StructuralGT/pytest/data/Rectangle1/img0.png
StructuralGT/pytest/data/Rectangle1/img1.png
StructuralGT/pytest/data/Rectangle1/img2.png
StructuralGT/pytest/data/Rectangle1/img3.png
StructuralGT/pytest/data/Rectangle1/img_options.json
sknwEdits/sknwEdits/sknwEdits.py
StructuralGTEdits-1.0.1b3.dist-info/LICENSE.txt
StructuralGTEdits-1.0.1b3.dist-info/METADATA
StructuralGTEdits-1.0.1b3.dist-info/WHEEL
StructuralGTEdits-1.0.1b3.dist-info/top_level.txt
StructuralGTEdits-1.0.1b3.dist-info/RECORD
