Metadata-Version: 2.1
Name: StructuralGTEdits
Version: 1.0.1b3
Summary: Automated graph theory analysis of digital structural networks images
Home-page: https://github.com/drewvecchio/StructuralGT
Author: drewvecchio
Author-email: vecdrew@umich.edu
License: GNU General Public License v3
License-File: LICENSE.txt
Requires-Dist: numpy
Requires-Dist: scipy
Requires-Dist: scikit-image
Requires-Dist: matplotlib
Requires-Dist: networkx
Requires-Dist: opencv-python
Requires-Dist: Pillow
Requires-Dist: pandas
Requires-Dist: cython
Requires-Dist: gsd
Requires-Dist: python-igraph
Requires-Dist: pytest
